ups/__init__.py
ups/_version.py
ups/cli.py
ups/xav.py
ups_api-0.1.0.dist-info/LICENSE
ups_api-0.1.0.dist-info/METADATA
ups_api-0.1.0.dist-info/WHEEL
ups_api-0.1.0.dist-info/entry_points.txt
ups_api-0.1.0.dist-info/top_level.txt
ups_api-0.1.0.dist-info/RECORD
