Metadata-Version: 2.1
Name: ups-api
Version: 0.1.0
Summary: Validate street addresses with the UPS API
Home-page: https://github.com/mcflugen/ups
Author: Eric Hutton
Author-email: huttone@colorado.edu
License: UNKNOWN
Platform: UNKNOWN
Classifier: License :: OSI Approved :: MIT License
Classifier: Operating System :: OS Independent
Classifier: Programming Language :: Python :: 3.6
Classifier: Programming Language :: Python :: 3.7
Requires-Dist: click
Requires-Dist: pandas
Requires-Dist: requests
